prediction/__init__.py
prediction/andreaUtils.py
prediction/andreaUtilsclustering.py
prediction/andreaUtilsprediction_v2.py
prediction/predictionarima.py
predictionconsoandrea-1.0.0.dist-info/METADATA
predictionconsoandrea-1.0.0.dist-info/WHEEL
predictionconsoandrea-1.0.0.dist-info/top_level.txt
predictionconsoandrea-1.0.0.dist-info/RECORD
